quasim/__init__.py
quasim/circuit.py
quasim/simulator.py
quasim/utils.py
quasim/gates/__init__.py
quasim/gates/_matrices.py
quasim/gates/controlled_gates.py
quasim/gates/double_controlled_gates.py
quasim/gates/interface.py
quasim/gates/single_qubit_gates.py
quasim/gates/swap.py
quasim/gates/utils.py
quasim-1.0.0.dist-info/LICENSE
quasim-1.0.0.dist-info/METADATA
quasim-1.0.0.dist-info/WHEEL
quasim-1.0.0.dist-info/top_level.txt
quasim-1.0.0.dist-info/RECORD
