Metadata-Version: 2.1
Name: quasim
Version: 1.0.0
Summary: Efficient simulation of quantum computing circuits.
Author: Christoph Stein
License: The MIT License (MIT)
Project-URL: Homepage, https://github.com/westoun/quasim
Project-URL: Issues, https://github.com/westoun/quasim/issues
Keywords: quantum,quantum computing,quantum computing simulator,simulation,simulator,quantum circuit simulator,quantum circuit
Classifier: License :: OSI Approved :: MIT License
Classifier: Programming Language :: Python
Classifier: Programming Language :: Python :: 3
Classifier: Operating System :: OS Independent
Requires-Python: >=3.9
License-File: LICENSE
Requires-Dist: numpy >=1.26.0
Provides-Extra: benchmark
Requires-Dist: qiskit ==0.45.1 ; extra == 'benchmark'
Requires-Dist: qiskit-aer ==0.13.1 ; extra == 'benchmark'
Requires-Dist: scipy ==1.13.0 ; extra == 'benchmark'
